graphitti/.ipynb_checkpoints/__init__-checkpoint.py
graphitti/__init__.py
graphitti/enzkin.py
graphitti-0.0.2.dist-info/METADATA
graphitti-0.0.2.dist-info/WHEEL
graphitti-0.0.2.dist-info/RECORD
