Metadata-Version: 2.1
Name: graphitti
Version: 0.0.2
Summary: Conveniences and wrappers for plotting graphs
License: AGPL-3.0
Author: kosmolebryce
Author-email: k.lebryce@pm.me
Requires-Python: >=3.9,<4.0
Classifier: License :: OSI Approved :: GNU Affero General Public License v3
Classifier: Programming Language :: Python :: 3
Classifier: Programming Language :: Python :: 3.9
Classifier: Programming Language :: Python :: 3.10
Classifier: Programming Language :: Python :: 3.11
Classifier: Programming Language :: Python :: 3.12
Classifier: Programming Language :: Python :: 3.13
Requires-Dist: matplotlib (>=3.9.3,<4.0.0)
Requires-Dist: seaborn (>=0.13.2,<0.14.0)
